snake_game_cli.py
snake_game_cli-0.1.2.dist-info/METADATA
snake_game_cli-0.1.2.dist-info/WHEEL
snake_game_cli-0.1.2.dist-info/entry_points.txt
snake_game_cli-0.1.2.dist-info/licenses/LICENSE
snake_game_cli-0.1.2.dist-info/RECORD
