Metadata-Version: 2.3
Name: snake-game-cli
Version: 0.1.2
Summary: Play snake game in CLI
Project-URL: Homepage, https://github.com/wang-hz/snake-game-cli
Author-email: "Wang H.Z." <imwanghz@gmail.com>
License-File: LICENSE
Classifier: License :: OSI Approved :: MIT License
Classifier: Operating System :: OS Independent
Classifier: Programming Language :: Python :: 3
Requires-Dist: windows-curses; sys_platform == 'win32'
